redcap_client/__init__.py
redcap_client/json.py
redcap_client/redcap.py
redcap_client/utils.py
redcap_client-0.1.2.dist-info/LICENSE
redcap_client-0.1.2.dist-info/WHEEL
redcap_client-0.1.2.dist-info/METADATA
redcap_client-0.1.2.dist-info/RECORD
