Metadata-Version: 2.1
Name: redcap-client
Version: 0.1.2
Summary: A fork of seattleflu/id3c containing only the redcap Project client
License: MIT
Author: Tom Thorogood
Author-email: goodtom@uw.edu
Requires-Python: >=3.6.2,<3.10
Classifier: License :: OSI Approved :: MIT License
Classifier: Programming Language :: Python :: 3
Classifier: Programming Language :: Python :: 3.7
Classifier: Programming Language :: Python :: 3.8
Classifier: Programming Language :: Python :: 3.9
Requires-Dist: requests (>=2.26.0,<3.0.0)
